LICENSE.md
README.md
pyproject.toml
setup.cfg
setup.py
rds_cep/__init__.py
rds_cep.egg-info/PKG-INFO
rds_cep.egg-info/SOURCES.txt
rds_cep.egg-info/dependency_links.txt
rds_cep.egg-info/requires.txt
rds_cep.egg-info/top_level.txt