Metadata-Version: 2.1
Name: rds-cep
Version: 0.0.1
Summary: Framework para serviços do Rede de Dados em Saúde do LAIS
Home-page: UNKNOWN
Author: Kelson da Costa Medeiros
Author-email: kelson.medeiros@lais.huol.ufrn.br
License: UNKNOWN
Keywords: rds,cache,config,helper,searchengine
Platform: UNKNOWN
Classifier: Development Status :: 5 - Production/Stable
Classifier: Intended Audience :: Developers
Classifier: License :: OSI Approved :: MIT License
Classifier: Operating System :: OS Independent
Classifier: Programming Language :: Python
Classifier: Programming Language :: Python :: 3.9
Classifier: Programming Language :: Python :: 3.10
Classifier: Programming Language :: Python :: 3.11
Classifier: Topic :: Software Development :: Libraries :: Python Modules
Classifier: Topic :: Internet :: WWW/HTTP :: Indexing/Search
Classifier: Topic :: Software Development :: Libraries
Requires-Python: >=3.9
License-File: LICENSE.md
